[
  {"id": "ADMIN-001", "category": "functional", "area": "admin", "description": "Admin can view user list", "steps": ["Log in as administrator", "Navigate to /admin/users", "Verify user list displayed", "Verify name, email, role columns"], "passes": true},
  {"id": "ADMIN-002", "category": "functional", "area": "admin", "description": "Admin can create new user", "steps": ["Log in as administrator", "Navigate to /admin/users/new", "Fill details", "Select role", "Submit", "Verify created"], "passes": true},
  {"id": "ADMIN-003", "category": "functional", "area": "admin", "description": "Admin can edit user", "steps": ["Log in as administrator", "Navigate to /admin/users", "Click Edit", "Modify details", "Submit", "Verify saved"], "passes": true},
  {"id": "ADMIN-004", "category": "functional", "area": "admin", "description": "Admin can change user role", "steps": ["Log in as administrator", "Edit user", "Change role from carer to nurse", "Submit", "Verify role updated"], "passes": true},
  {"id": "ADMIN-005", "category": "functional", "area": "admin", "description": "Admin can deactivate user", "steps": ["Log in as administrator", "Click Deactivate for user", "Confirm", "Verify marked inactive", "Verify user cannot log in"], "passes": true},
  {"id": "ADMIN-006", "category": "functional", "area": "admin", "description": "Admin can activate user", "steps": ["Log in as administrator", "Find deactivated user", "Click Activate", "Verify marked active", "Verify user can log in"], "passes": true},
  {"id": "ADMIN-007", "category": "functional", "area": "admin", "description": "Admin can search users by name", "steps": ["Log in as administrator", "Enter name in search", "Submit", "Verify results match"], "passes": true},
  {"id": "ADMIN-008", "category": "functional", "area": "admin", "description": "Admin can search users by email", "steps": ["Log in as administrator", "Enter email in search", "Submit", "Verify results match"], "passes": true},
  {"id": "ADMIN-009", "category": "functional", "area": "admin", "description": "Admin can filter users by role", "steps": ["Log in as administrator", "Select carer from role filter", "Submit", "Verify only carers shown"], "passes": true},
  {"id": "ADMIN-010", "category": "functional", "area": "admin", "description": "Admin can filter users by active status", "steps": ["Log in as administrator", "Select inactive from status filter", "Submit", "Verify only inactive users shown"], "passes": true},
  {"id": "ADMIN-011", "category": "functional", "area": "admin", "description": "Admin user list is paginated (20 per page)", "steps": ["Ensure >20 users exist", "Log in as administrator", "Navigate to /admin/users", "Verify 20 per page", "Click Next", "Verify next page"], "passes": true},
  {"id": "ADMIN-012", "category": "functional", "area": "admin", "description": "Admin can sort users by name", "steps": ["Log in as administrator", "Click Name column header", "Verify sorted ascending", "Click again", "Verify sorted descending"], "passes": true},
  {"id": "ADMIN-013", "category": "functional", "area": "admin", "description": "Admin can sort users by email", "steps": ["Log in as administrator", "Click Email column header", "Verify sorted"], "passes": true},
  {"id": "ADMIN-014", "category": "functional", "area": "admin", "description": "Admin can sort users by created_at", "steps": ["Log in as administrator", "Click Created column header", "Verify sorted by date"], "passes": true},
  {"id": "ADMIN-015", "category": "functional", "area": "admin", "description": "Admin can create user with nested person", "steps": ["Log in as administrator", "Navigate to /admin/users/new", "Fill user email/password", "Fill person name/DOB", "Submit", "Verify user created", "Verify person linked"], "passes": true},
  {"id": "ADMIN-016", "category": "functional", "area": "admin", "description": "Admin dashboard shows total users by role", "steps": ["Log in as administrator", "Navigate to /admin/dashboard", "Verify administrator count", "Verify doctor count", "Verify nurse count", "Verify carer count", "Verify parent count"], "passes": true},
  {"id": "ADMIN-017", "category": "functional", "area": "admin", "description": "Admin dashboard shows total people by type", "steps": ["Log in as administrator", "Navigate to /admin/dashboard", "Verify adult count", "Verify minor count", "Verify dependent adult count"], "passes": true},
  {"id": "ADMIN-018", "category": "functional", "area": "admin", "description": "Admin dashboard shows recent signups (last 7 days)", "steps": ["Log in as administrator", "Navigate to /admin/dashboard", "Verify recent signups shown"], "passes": true},
  {"id": "ADMIN-019", "category": "functional", "area": "admin", "description": "Admin dashboard shows active users count", "steps": ["Log in as administrator", "Navigate to /admin/dashboard", "Verify active users count displayed"], "passes": true},
  {"id": "ADMIN-020", "category": "functional", "area": "admin", "description": "Admin dashboard warns about patients without carers", "steps": ["Create patient without capacity and no carer", "Log in as administrator", "Navigate to /admin/dashboard", "Verify warning displayed"], "passes": true},
  {"id": "ADMIN-021", "category": "functional", "area": "admin", "description": "Admin dashboard has quick links to manage users", "steps": ["Log in as administrator", "Navigate to /admin/dashboard", "Verify link to /admin/users", "Click link", "Verify navigates"], "passes": true},
  {"id": "ADMIN-022", "category": "functional", "area": "admin", "description": "Complete admin user management workflow", "steps": ["Log in as administrator (damacus@example.com)", "Navigate to /admin/users", "Verify user list displayed with columns", "Click New User button", "Fill in email: newuser@example.com", "Fill in password: SecurePass123", "Fill in person name: New Test User", "Fill in date of birth", "Select role: nurse", "Submit form", "Verify success message", "Verify user appears in list", "Click Edit on new user", "Change role to doctor", "Submit changes", "Verify role updated", "Click Deactivate", "Confirm deactivation", "Verify user marked inactive", "Click Activate", "Verify user marked active again"], "passes": false},
  {"id": "ADMIN-023", "category": "functional", "area": "admin", "description": "Admin search and filter combined workflow", "steps": ["Log in as administrator", "Navigate to /admin/users", "Enter search term in name field", "Select role filter: carer", "Select status filter: active", "Submit search", "Verify results match all criteria", "Clear filters", "Verify all users shown again", "Click Name column to sort ascending", "Verify sorted A-Z", "Click Name column again to sort descending", "Verify sorted Z-A", "Navigate to page 2 if available", "Verify pagination works correctly"], "passes": false}
]
